docx_replace_package_alexgarden92160/__init__.py
docx_replace_package_alexgarden92160/app.py
docx_replace_package_alexgarden92160-1.0.0.dist-info/METADATA
docx_replace_package_alexgarden92160-1.0.0.dist-info/WHEEL
docx_replace_package_alexgarden92160-1.0.0.dist-info/licenses/LICENSE
docx_replace_package_alexgarden92160-1.0.0.dist-info/RECORD
